bean_mortgage.py
bean_mortgage-0.2.dist-info/entry_points.txt
bean_mortgage-0.2.dist-info/LICENSE
bean_mortgage-0.2.dist-info/WHEEL
bean_mortgage-0.2.dist-info/METADATA
bean_mortgage-0.2.dist-info/RECORD
