Metadata-Version: 2.1
Name: bean_mortgage
Version: 0.2
Summary: A small utility to create mortgage schedules for beancount.
Author-email: Gerry Agbobada <pypi@gagbo.net>
Requires-Python: >=3.7,<4
Classifier: License :: OSI Approved :: MIT License
Requires-Dist: python-dateutil >= 2.8
Project-URL: Documentation, https://git.sr.ht/~gagbo/bean_mortgage
Project-URL: Source, https://git.sr.ht/~gagbo/bean_mortgage
